[
  {
    "ApiId": "/providers/microsoft.powerapps/apis/shared_sharepointonline",
    "CdpRevision": {
      "BaseUrl": "/",
      "LastChangedTimeString": "2022-06-02T17:39:24.1330000Z",
      "RevisionNumber": 1
    },
    "ConnectedDataSourceInfoNameMapping": {},
    "DatasetName": "https://3dtechnology.sharepoint.com/sites/Innovation",
    "EncodeDataset": true,
    "IsSampleData": false,
    "IsWritable": true,
    "Name": "QHC - Critical Incident Management",
    "Type": "ConnectedDataSourceInfo"
  }
]